setup.py
panopta_rest_api/__init__.py
panopta_rest_api/api_client.py
panopta_rest_api/test_api_client.py
panopta_rest_api.egg-info/PKG-INFO
panopta_rest_api.egg-info/SOURCES.txt
panopta_rest_api.egg-info/dependency_links.txt
panopta_rest_api.egg-info/requires.txt
panopta_rest_api.egg-info/top_level.txt