Metadata-Version: 1.0
Name: panopta-rest-api
Version: 1.0.1
Summary: Panopta REST API Client
Home-page: http://www.panopta.com
Author: Panopta
Author-email: support@panopta.com
License: UNKNOWN
Platform: UNKNOWN
